{
  "topic_slug": "geopolitics",
  "topic_title": "Global Geopolitics Monitor",
  "data_type": "rss_feed_content",
  "enabled_data_types": [
    "news_articles",
    "government_documents",
    "research_papers",
    "books",
    "pdfs",
    "rss_feed_content",
    "structured_datasets",
    "websites_html_pages",
    "blogs",
    "video_content",
    "video_transcripts",
    "audio_content",
    "images",
    "ocr_text",
    "legal_judicial_records",
    "financial_data",
    "scientific_technical_data",
    "geospatial_mapping_data",
    "event_data",
    "timeline_data",
    "entity_data",
    "relationship_data",
    "metrics_numerical_data",
    "metadata",
    "archived_historical_content",
    "open_source_intelligence",
    "web_archives_cached_content"
  ],
  "url": "https://reliefweb.int/report/world/empowering-women-during-humanitarian-crises",
  "title": "World: Empowering women during humanitarian crises",
  "source": "https://reliefweb.int/updates/rss.xml",
  "published": "Tue, 26 May 2026 21:03:08 +0000",
  "sha256": "7b5965829efe14d8473c6ea002298722e9e896296e9af9eab9c185949b263518",
  "content_type": "text/html; charset=UTF-8",
  "collected_at": "2026-05-27T10:54:34.098168+00:00",
  "text_chars": 9256,
  "raw_path": "data/geopolitics/raw/7b5965829efe14d8473c6ea002298722e9e896296e9af9eab9c185949b263518.html",
  "text_path": "data/geopolitics/raw/7b5965829efe14d8473c6ea002298722e9e896296e9af9eab9c185949b263518.txt"
}