{
  "topic_slug": "geopolitics",
  "topic_title": "Global Geopolitics Monitor",
  "data_type": "rss_feed_content",
  "enabled_data_types": [
    "news_articles",
    "government_documents",
    "research_papers",
    "books",
    "pdfs",
    "rss_feed_content",
    "structured_datasets",
    "websites_html_pages",
    "blogs",
    "video_content",
    "video_transcripts",
    "audio_content",
    "images",
    "ocr_text",
    "legal_judicial_records",
    "financial_data",
    "scientific_technical_data",
    "geospatial_mapping_data",
    "event_data",
    "timeline_data",
    "entity_data",
    "relationship_data",
    "metrics_numerical_data",
    "metadata",
    "archived_historical_content",
    "open_source_intelligence",
    "web_archives_cached_content"
  ],
  "url": "http://www.euronews.com/2026/05/27/ukraines-drone-commander-warns-lukashenka-about-500-potential-targets-in-belarus",
  "title": "Ukraine’s drone commander warns Lukashenka about 500 potential targets in Belarus",
  "source": "https://www.euronews.com/rss?level=theme&name=news",
  "published": "Wed, 27 May 2026 09:41:20 +0200",
  "sha256": "c8d9a231b6a7ef6f2d9757b9779ca1a595ac67509ac24a38c954468c65c53632",
  "content_type": "text/html; charset=UTF-8",
  "collected_at": "2026-05-27T10:54:42.294828+00:00",
  "text_chars": 2760,
  "raw_path": "data/geopolitics/raw/c8d9a231b6a7ef6f2d9757b9779ca1a595ac67509ac24a38c954468c65c53632.html",
  "text_path": "data/geopolitics/raw/c8d9a231b6a7ef6f2d9757b9779ca1a595ac67509ac24a38c954468c65c53632.txt"
}